{
    "error_message": "MES ENVIRONMENT CRASHING - EXCEPTION FOLLOWS \n\tSource Message: <Message Sender: , Recipients: , Directive: contract, Content: ('barg_agent.BargAgent 1', 'barg_agent.BargAgent 2', 595)>\n\tError Type: <class 'AttributeError'>\n\tError: 'BargEnvironment' object has no attribute 'dispatcher'\n\n\tTrace Output: \n\t  File \"/mtree/mTree/microeconomic_system/environment.py\", line 217, in receiveMessage\n    directive_handler(self, message)\n\n\t  File \"barg_environment.py\", line 93, in contract\n\n\t  File \"/mtree/mTree/microeconomic_system/environment.py\", line 157, in shutdown_mes\n    self.send(self.dispatcher, new_message)\n\n",
    "source_message": "<Message Sender: , Recipients: , Directive: contract, Content: ('barg_agent.BargAgent 1', 'barg_agent.BargAgent 2', 595)>",
    "error_type": "<class 'AttributeError'>",
    "error": "'BargEnvironment' object has no attribute 'dispatcher'",
    "filename": "/mtree/mTree/microeconomic_system/environment.py",
    "lineno": 217,
    "name": "receiveMessage",
    "line": "directive_handler(self, message)"
}